gwc/__init__.py
gwc/__version__.py
gwc/authpolicy.py
gwc/globals.py
gwc/gwc_scripts.py
gwc/login.py
gwc/utility.py
gwc/common/__init__.py
gwc/common/excel_loader.py
gwc/runners/__init__.py
gwc/runners/_base.py
gwc/runners/gwl.py
gwc/runners/wdl.py
gwc-0.4.7.dist-info/METADATA
gwc-0.4.7.dist-info/WHEEL
gwc-0.4.7.dist-info/entry_points.txt
gwc-0.4.7.dist-info/pbr.json
gwc-0.4.7.dist-info/top_level.txt
gwc-0.4.7.dist-info/RECORD
