Metadata-Version: 2.1
Name: gwc
Version: 0.4.7
Summary: GeneDock command-line workflow client for interacting with GeneDock platform
Home-page: https://gitlab.genedock.com/genedock/gwc
Author: genedock
Author-email: gwc@genedock.com
License: UNKNOWN
Platform: UNKNOWN
Classifier: Intended Audience :: Developers
Classifier: Operating System :: OS Independent
Classifier: Programming Language :: Python
Classifier: Programming Language :: Python :: 2
Classifier: Programming Language :: Python :: 2.6
Classifier: Programming Language :: Python :: 2.7
Classifier: Programming Language :: Python :: 3
Classifier: Programming Language :: Python :: 3.3
Classifier: Programming Language :: Python :: 3.4
Classifier: Programming Language :: Python :: 3.5
Requires-Dist: gdpy (>=0.1.10)
Requires-Dist: prettytable (==0.7.2)
Requires-Dist: gddriver (<0.3.0,>=0.2.10)
Requires-Dist: pytz (==2019.3)
Requires-Dist: python-dateutil (==2.6.0)
Requires-Dist: openpyxl (>=2.6.4)
Requires-Dist: pbr (>=5.8.0)
